python_udemy-0.0.2.dist-info/DESCRIPTION.rst
python_udemy-0.0.2.dist-info/entry_points.txt
python_udemy-0.0.2.dist-info/METADATA
python_udemy-0.0.2.dist-info/metadata.json
python_udemy-0.0.2.dist-info/RECORD
python_udemy-0.0.2.dist-info/top_level.txt
python_udemy-0.0.2.dist-info/WHEEL
udemy/__init__.py
udemy/cli.py
